playwrightnb/__init__.py
playwrightnb/_modidx.py
playwrightnb/core.py
playwrightnb/patch.py
playwrightnb-0.2.2.dist-info/METADATA
playwrightnb-0.2.2.dist-info/WHEEL
playwrightnb-0.2.2.dist-info/entry_points.txt
playwrightnb-0.2.2.dist-info/top_level.txt
playwrightnb-0.2.2.dist-info/RECORD
