Metadata-Version: 2.1
Name: playwrightnb
Version: 0.2.2
Summary: Helpers for using Playwright from notebooks and more
Home-page: https://github.com/AnswerDotAI/playwrightnb
Author: Jeremy Howard
Author-email: info@fast.ai
License: Apache Software License 2.0
Keywords: nbdev jupyter notebook python playwright
Classifier: Development Status :: 4 - Beta
Classifier: Intended Audience :: Developers
Classifier: Natural Language :: English
Classifier: Programming Language :: Python :: 3.8
Classifier: Programming Language :: Python :: 3.9
Classifier: Programming Language :: Python :: 3.10
Classifier: Programming Language :: Python :: 3.11
Classifier: Programming Language :: Python :: 3.12
Classifier: License :: OSI Approved :: Apache Software License
Requires-Python: >=3.8
Requires-Dist: fastcore
Requires-Dist: playwright
Requires-Dist: playwright-stealth
Requires-Dist: anyio
Requires-Dist: html2text
Requires-Dist: beautifulsoup4
Requires-Dist: httpx
Provides-Extra: dev
